{
    "name": "Transgender-Crossdressers",
    "files": [
        {
            "title": "Family Issues Ch. 13",
            "file": "0.json"
        },
        {
            "title": "Stray Cats Ch. 06",
            "file": "1.json"
        },
        {
            "title": "Tribal Bonds Ch. 06",
            "file": "2.json"
        },
        {
            "title": "Down the Rabbit Hole Ch. 05",
            "file": "3.json"
        },
        {
            "title": "Is She Smiling at Me? Pt. 06",
            "file": "4.json"
        },
        {
            "title": "Is She Smiling at Me? Pt. 07",
            "file": "5.json"
        },
        {
            "title": "Family Issues Ch. 09",
            "file": "6.json"
        },
        {
            "title": "Women's Studies Ch. 15",
            "file": "7.json"
        },
        {
            "title": "The Letter",
            "file": "8.json"
        },
        {
            "title": "Molly's Muse Pt. 02",
            "file": "9.json"
        },
        {
            "title": "Ambiramus Ch. 02",
            "file": "10.json"
        },
        {
            "title": "Is She Smiling at Me? Pt. 03 Ch. 03",
            "file": "11.json"
        },
        {
            "title": "Ambiramus Ch. 05",
            "file": "12.json"
        },
        {
            "title": "Nerdcam Pt. 03",
            "file": "13.json"
        },
        {
            "title": "Ambiramus Ch. 06",
            "file": "14.json"
        },
        {
            "title": "Molly's Muse Pt. 01",
            "file": "15.json"
        },
        {
            "title": "Nerdcam Pt. 02",
            "file": "16.json"
        },
        {
            "title": "Lily in Bloom",
            "file": "17.json"
        },
        {
            "title": "Sanctum of Defilement",
            "file": "18.json"
        },
        {
            "title": "Family Issues Ch. 04",
            "file": "19.json"
        },
        {
            "title": "Big Flipping Deal Ch. 07",
            "file": "20.json"
        },
        {
            "title": "Maybe, It Gets Better",
            "file": "21.json"
        },
        {
            "title": "Mary Janes",
            "file": "22.json"
        },
        {
            "title": "The Sultanah Ch. 14",
            "file": "23.json"
        },
        {
            "title": "Roommate - Huge Changes Ch. 03",
            "file": "24.json"
        },
        {
            "title": "Enemy From Below",
            "file": "25.json"
        },
        {
            "title": "Shadows in the Moonlight",
            "file": "26.json"
        },
        {
            "title": "Son for Hire Ch. 01-11",
            "file": "27.json"
        },
        {
            "title": "Pledging Tau Geta Delta Pt. 05",
            "file": "28.json"
        },
        {
            "title": "Once you go Black.. Pt. 02",
            "file": "29.json"
        },
        {
            "title": "Pledging Tau Geta Delta Pt. 04",
            "file": "30.json"
        },
        {
            "title": "Emelie's Quest for Futanari Cock",
            "file": "31.json"
        },
        {
            "title": "A Pleasant Surprise Pt. 05",
            "file": "32.json"
        },
        {
            "title": "Is She Smiling at Me? Pt. 05",
            "file": "33.json"
        },
        {
            "title": "The Agency Ch. 11",
            "file": "34.json"
        },
        {
            "title": "Freshman Bride Pt. 05 - Getaway",
            "file": "35.json"
        },
        {
            "title": "The Writer's Muse Ch. 02",
            "file": "36.json"
        },
        {
            "title": "Secrets and Surrender",
            "file": "37.json"
        },
        {
            "title": "Family Issues Ch. 06",
            "file": "38.json"
        },
        {
            "title": "Women's Studies Ch. 03",
            "file": "39.json"
        },
        {
            "title": "Women's Studies Ch. 12",
            "file": "40.json"
        },
        {
            "title": "Women's Studies Ch. 06",
            "file": "41.json"
        },
        {
            "title": "Women's Studies Ch. 10",
            "file": "42.json"
        },
        {
            "title": "The Sultanah Ch. 04",
            "file": "43.json"
        },
        {
            "title": "The Family Pt. 01",
            "file": "44.json"
        },
        {
            "title": "Halftime",
            "file": "45.json"
        },
        {
            "title": "Room for Mickie Ch. 05",
            "file": "46.json"
        },
        {
            "title": "Marion's Story Ch. 17",
            "file": "47.json"
        },
        {
            "title": "Pledging Tau Geta Delta Pt. 03",
            "file": "48.json"
        },
        {
            "title": "Stray Cats Ch. 03",
            "file": "49.json"
        },
        {
            "title": "It's Complicated",
            "file": "50.json"
        },
        {
            "title": "Lumberyard Miracle",
            "file": "51.json"
        },
        {
            "title": "Rear Window Homage",
            "file": "52.json"
        },
        {
            "title": "Violet Iodine",
            "file": "53.json"
        },
        {
            "title": "Results and Consequences",
            "file": "54.json"
        },
        {
            "title": "Is She Smiling at Me? Pt. 03 Ch. 02",
            "file": "55.json"
        },
        {
            "title": "An Almost Normal Life Ch. 02",
            "file": "56.json"
        },
        {
            "title": "Exploring the Bounds of Normal",
            "file": "57.json"
        },
        {
            "title": "My Name is Raquel Ch. 05",
            "file": "58.json"
        },
        {
            "title": "Finding the Perfect Fit Pt. 15",
            "file": "59.json"
        },
        {
            "title": "Futa's Wild Passion Ch. 07",
            "file": "60.json"
        },
        {
            "title": "The Agency Ch. 14",
            "file": "61.json"
        },
        {
            "title": "Losing It Ch. 04",
            "file": "62.json"
        },
        {
            "title": "Women's Studies Ch. 05",
            "file": "63.json"
        },
        {
            "title": "Halloween: A Pussycat's Tail",
            "file": "64.json"
        },
        {
            "title": "Trans Summer",
            "file": "65.json"
        },
        {
            "title": "The Sultanah Ch. 03",
            "file": "66.json"
        },
        {
            "title": "Pursued by a Dominant T-girl",
            "file": "67.json"
        },
        {
            "title": "The Fappening",
            "file": "68.json"
        },
        {
            "title": "The unexpected housekeeper Ch. 02",
            "file": "69.json"
        },
        {
            "title": "Sexual Sissy Awakening",
            "file": "70.json"
        },
        {
            "title": "The Sultanah Ch. 10",
            "file": "71.json"
        },
        {
            "title": "The Sultanah Ch. 05",
            "file": "72.json"
        },
        {
            "title": "My Journey Ch. 05",
            "file": "73.json"
        },
        {
            "title": "From Friendship Comes Love Pt. 02",
            "file": "74.json"
        },
        {
            "title": "The Journey",
            "file": "75.json"
        },
        {
            "title": "Changing Rooms Ch. 02",
            "file": "76.json"
        },
        {
            "title": "Marion's Story Ch. 06",
            "file": "77.json"
        },
        {
            "title": "A Pleasant Surprise Pt. 03",
            "file": "78.json"
        },
        {
            "title": "Divination and Manipulation Pt. 02",
            "file": "79.json"
        },
        {
            "title": "The Agency Ch. 08",
            "file": "80.json"
        },
        {
            "title": "Stray Cats Ch. 02",
            "file": "81.json"
        },
        {
            "title": "Something about Me and You Pt. 02",
            "file": "82.json"
        },
        {
            "title": "Pea Pod - The Return",
            "file": "83.json"
        },
        {
            "title": "The Agency Ch. 09",
            "file": "84.json"
        },
        {
            "title": "Orchid Ch. 02",
            "file": "85.json"
        },
        {
            "title": "Witness Ch. 04",
            "file": "86.json"
        },
        {
            "title": "Made to Order Ch. 03",
            "file": "87.json"
        },
        {
            "title": "A Game of HORSE Pt. 05",
            "file": "88.json"
        },
        {
            "title": "Futa's Wild Passion Ch. 05",
            "file": "89.json"
        },
        {
            "title": "The Lost Boy Ch. 12",
            "file": "90.json"
        },
        {
            "title": "The Society Ch. 04",
            "file": "91.json"
        },
        {
            "title": "Down the Rabbit Hole Ch. 04",
            "file": "92.json"
        },
        {
            "title": "Tribal Bonds Ch. 03",
            "file": "93.json"
        },
        {
            "title": "Loving Yvonne",
            "file": "94.json"
        },
        {
            "title": "Down the Rabbit Hole",
            "file": "95.json"
        },
        {
            "title": "An Almost Normal Life Ch. 01",
            "file": "96.json"
        },
        {
            "title": "A Romantic Story",
            "file": "97.json"
        },
        {
            "title": "Escalating Series of Surprises Ch. 01",
            "file": "98.json"
        },
        {
            "title": "Hermaphrodite Ch. 02",
            "file": "99.json"
        },
        {
            "title": "The Next Level",
            "file": "100.json"
        },
        {
            "title": "Four Blessings Pt. 02",
            "file": "101.json"
        },
        {
            "title": "Joining a Fraternity Ch. 03",
            "file": "102.json"
        },
        {
            "title": "A Game of Basketball Pt. 09",
            "file": "103.json"
        },
        {
            "title": "Uncovering Jamie",
            "file": "104.json"
        },
        {
            "title": "Hampton Heights",
            "file": "105.json"
        },
        {
            "title": "My Journey Ch. 04",
            "file": "106.json"
        },
        {
            "title": "Mia Mine Ch. 06",
            "file": "107.json"
        },
        {
            "title": "Uncovering Jamie Ch. 02: A Sunday Treat",
            "file": "108.json"
        },
        {
            "title": "The Agency Ch. 06",
            "file": "109.json"
        },
        {
            "title": "The Agency Ch. 07",
            "file": "110.json"
        },
        {
            "title": "On Vacation - An X-Change Novella Ch. 02",
            "file": "111.json"
        },
        {
            "title": "The Treehouse Pt. 03",
            "file": "112.json"
        },
        {
            "title": "Lonely in Berlin",
            "file": "113.json"
        },
        {
            "title": "A Highly Recommended Urologist Ch. 04",
            "file": "114.json"
        },
        {
            "title": "Freshman Bride Pt. 03 - Girlfriend?",
            "file": "115.json"
        },
        {
            "title": "My Journey Ch. 09",
            "file": "116.json"
        },
        {
            "title": "Homecoming Queen Ch. 03",
            "file": "117.json"
        },
        {
            "title": "Jeanie's Lamp Ch. 04",
            "file": "118.json"
        },
        {
            "title": "Ambiramus Ch. 04",
            "file": "119.json"
        },
        {
            "title": "The Change Pt. 05",
            "file": "120.json"
        },
        {
            "title": "The Slave's Conquest",
            "file": "121.json"
        },
        {
            "title": "A Visit to the North Ch. 05",
            "file": "122.json"
        },
        {
            "title": "My New Girl? Ch. 05",
            "file": "123.json"
        },
        {
            "title": "A Game of HORSE Pt. 04",
            "file": "124.json"
        },
        {
            "title": "David and Jess Ch. 05",
            "file": "125.json"
        },
        {
            "title": "Big U Pride Ch. 02: Going Deeper",
            "file": "126.json"
        },
        {
            "title": "The Ballad of Jaimie and Vera Ch. 03",
            "file": "127.json"
        },
        {
            "title": "Tribal Bonds Ch. 02",
            "file": "128.json"
        },
        {
            "title": "The Lost Boy Ch. 14",
            "file": "129.json"
        },
        {
            "title": "Stray Cats Ch. 05",
            "file": "130.json"
        },
        {
            "title": "Cockatoo Pt. 36",
            "file": "131.json"
        },
        {
            "title": "Divisional Rivals Ch. 03",
            "file": "132.json"
        },
        {
            "title": "Making a Sissy Jock Pt. 03",
            "file": "133.json"
        },
        {
            "title": "A Year Ago Ch. 18",
            "file": "134.json"
        },
        {
            "title": "Futa's Wild Passion Ch. 08",
            "file": "135.json"
        },
        {
            "title": "Working Out Issues Ch. 08",
            "file": "136.json"
        },
        {
            "title": "The New Neighbor Ch. 02",
            "file": "137.json"
        },
        {
            "title": "The Agency Ch. 13",
            "file": "138.json"
        },
        {
            "title": "A Clockwork Green Ch. 04",
            "file": "139.json"
        },
        {
            "title": "A Clockwork Green Ch. 12",
            "file": "140.json"
        },
        {
            "title": "Hermaphrodite",
            "file": "141.json"
        },
        {
            "title": "A Boiled Frog Pt. 03",
            "file": "142.json"
        },
        {
            "title": "The Sissy Mark",
            "file": "143.json"
        },
        {
            "title": "A Boiled Frog Pt. 06",
            "file": "144.json"
        },
        {
            "title": "Big Flipping Deal Ch. 05",
            "file": "145.json"
        },
        {
            "title": "A Boiled Frog Pt. 04",
            "file": "146.json"
        },
        {
            "title": "Making Work a Better Place Ch. 06",
            "file": "147.json"
        },
        {
            "title": "Anal Addiction Ch. 03",
            "file": "148.json"
        },
        {
            "title": "I Like That It's You",
            "file": "149.json"
        },
        {
            "title": "Voluntary Beauty",
            "file": "150.json"
        },
        {
            "title": "A Highly Recommended Urologist Ch. 02",
            "file": "151.json"
        },
        {
            "title": "My Wife's Big Dick",
            "file": "152.json"
        },
        {
            "title": "Victoria's Secrets",
            "file": "153.json"
        },
        {
            "title": "Trick or Trini",
            "file": "154.json"
        },
        {
            "title": "Amanda and Me Ch. 07",
            "file": "155.json"
        },
        {
            "title": "Breaking Up and Making Up",
            "file": "156.json"
        },
        {
            "title": "The Sultanah Ch. 11",
            "file": "157.json"
        },
        {
            "title": "The Sultanah Ch. 07",
            "file": "158.json"
        },
        {
            "title": "Milking The Bull Ch. 02",
            "file": "159.json"
        },
        {
            "title": "Amber's Ambush",
            "file": "160.json"
        },
        {
            "title": "The Sultanah Ch. 08",
            "file": "161.json"
        },
        {
            "title": "Serendipity",
            "file": "162.json"
        },
        {
            "title": "Love Training Pt. 02",
            "file": "163.json"
        },
        {
            "title": "Claimed by a Futa Genie",
            "file": "164.json"
        },
        {
            "title": "More than Friends Pt. 01",
            "file": "165.json"
        },
        {
            "title": "Pledging Tau Geta Delta Pt. 02",
            "file": "166.json"
        },
        {
            "title": "The Surrogate Ch. 05",
            "file": "167.json"
        },
        {
            "title": "A Pair of Objects Walk into a Bar",
            "file": "168.json"
        },
        {
            "title": "My Life Pt. 06",
            "file": "169.json"
        },
        {
            "title": "Born to Be Ch. 05",
            "file": "170.json"
        },
        {
            "title": "An Unexpected Opportunity",
            "file": "171.json"
        },
        {
            "title": "Walk a Crooked Milf Ch. 06",
            "file": "172.json"
        },
        {
            "title": "A Dish Best Served Cold Ch. 04",
            "file": "173.json"
        },
        {
            "title": "My One True Love Ch. 08",
            "file": "174.json"
        },
        {
            "title": "USB - Unwanted Sexual Behavior Ch. 04",
            "file": "175.json"
        },
        {
            "title": "Futa's Wild Passion Ch. 04",
            "file": "176.json"
        },
        {
            "title": "Red Wolf",
            "file": "177.json"
        },
        {
            "title": "One for the Team Ch. 03",
            "file": "178.json"
        },
        {
            "title": "The Agency Ch. 12",
            "file": "179.json"
        },
        {
            "title": "Cockatoo Pt. 32",
            "file": "180.json"
        },
        {
            "title": "The Agency Ch. 15",
            "file": "181.json"
        },
        {
            "title": "A Visit to the North Ch. 10",
            "file": "182.json"
        },
        {
            "title": "She-Male School: A Teacher Seduced",
            "file": "183.json"
        },
        {
            "title": "Blackmail",
            "file": "184.json"
        },
        {
            "title": "Your Eternal Reward",
            "file": "185.json"
        },
        {
            "title": "The Neighbors Ch. 02",
            "file": "186.json"
        },
        {
            "title": "A Boiled Frog Pt. 05",
            "file": "187.json"
        },
        {
            "title": "Bah Humbug",
            "file": "188.json"
        },
        {
            "title": "Women's Studies Ch. 14",
            "file": "189.json"
        },
        {
            "title": "From Friendship Comes Love Pt. 01",
            "file": "190.json"
        },
        {
            "title": "Futanari Breeding Agency Ch. 03",
            "file": "191.json"
        },
        {
            "title": "Stray Cats Ch. 04",
            "file": "192.json"
        },
        {
            "title": "Glory Beyond the Hole",
            "file": "193.json"
        },
        {
            "title": "Family Issues Ch. 08",
            "file": "194.json"
        },
        {
            "title": "Is She Smiling at Me? Pt. 04 Ch. 02",
            "file": "195.json"
        },
        {
            "title": "Jeanie's Lamp Ch. 05",
            "file": "196.json"
        },
        {
            "title": "Finding the Perfect Fit Pt. 17",
            "file": "197.json"
        },
        {
            "title": "Red Swallow Ch. 04",
            "file": "198.json"
        },
        {
            "title": "Kayla the Bull Ch. 04",
            "file": "199.json"
        },
        {
            "title": "Family Issues Ch. 05",
            "file": "200.json"
        },
        {
            "title": "Family Issues Ch. 10",
            "file": "201.json"
        },
        {
            "title": "Big Flipping Deal Ch. 06",
            "file": "202.json"
        },
        {
            "title": "The Looking Glass",
            "file": "203.json"
        },
        {
            "title": "Women's Studies Ch. 11",
            "file": "204.json"
        },
        {
            "title": "Women's Studies Ch. 13",
            "file": "205.json"
        },
        {
            "title": "My Queer Cousins: A novella",
            "file": "206.json"
        },
        {
            "title": "Adventures of Hiking Ch. 02",
            "file": "207.json"
        },
        {
            "title": "On Vacation - An X-Change Novella Ch. 01",
            "file": "208.json"
        },
        {
            "title": "The Interview",
            "file": "209.json"
        },
        {
            "title": "Orchid Ch. 01",
            "file": "210.json"
        },
        {
            "title": "Pledging Tau Geta Delta Pt. 07",
            "file": "211.json"
        },
        {
            "title": "The Surrogate Ch. 06",
            "file": "212.json"
        },
        {
            "title": "Watching the Detectives",
            "file": "213.json"
        },
        {
            "title": "Keep Practising",
            "file": "214.json"
        },
        {
            "title": "When Wishes Come True",
            "file": "215.json"
        },
        {
            "title": "Pledging Tau Geta Delta Pt. 06",
            "file": "216.json"
        },
        {
            "title": "Mia Mine Ch. 13",
            "file": "217.json"
        },
        {
            "title": "Ambiramus Ch. 03",
            "file": "218.json"
        },
        {
            "title": "Mia Mine Ch. 12",
            "file": "219.json"
        },
        {
            "title": "The Futanari Diaries Ch. 02",
            "file": "220.json"
        },
        {
            "title": "Orchid Ch. 03",
            "file": "221.json"
        },
        {
            "title": "Stray Cats Ch. 07 - Final Chapter",
            "file": "222.json"
        },
        {
            "title": "Camming Down the Rabbit Hole Ch. 03",
            "file": "223.json"
        },
        {
            "title": "Cockatoo Pt. 44",
            "file": "224.json"
        },
        {
            "title": "Finding the Perfect Fit Pt. 16",
            "file": "225.json"
        },
        {
            "title": "A Game of HORSE Pt. 07",
            "file": "226.json"
        },
        {
            "title": "Finding the Perfect Fit Pt. 20",
            "file": "227.json"
        },
        {
            "title": "Women's Studies Ch. 07",
            "file": "228.json"
        },
        {
            "title": "Women's Studies Ch. 09",
            "file": "229.json"
        },
        {
            "title": "A Boiled Frog Pt. 02",
            "file": "230.json"
        },
        {
            "title": "Charlie",
            "file": "231.json"
        },
        {
            "title": "The Sultanah Ch. 02",
            "file": "232.json"
        },
        {
            "title": "Danielle",
            "file": "233.json"
        },
        {
            "title": "Ambiramus Ch. 01",
            "file": "234.json"
        },
        {
            "title": "The Sultanah Ch. 06",
            "file": "235.json"
        },
        {
            "title": "The Sultanah Ch. 09",
            "file": "236.json"
        },
        {
            "title": "Trini Trims the Tree",
            "file": "237.json"
        },
        {
            "title": "The Sultanah Ch. 12",
            "file": "238.json"
        }
    ]
}